Metadata-Version: 2.1
Name: gfpgan-patch
Version: 1.3.8
Summary: GFPGAN aims at developing Practical Algorithms for Real-world Face Restoration
Home-page: https://github.com/wwdok/GFPGAN
Author: Xintao Wang
Author-email: xintao.wang@outlook.com
License: Apache License Version 2.0
Keywords: computer vision,pytorch,image restoration,super-resolution,face restoration,gan,gfpgan
Classifier: Development Status :: 4 - Beta
Classifier: License :: OSI Approved :: Apache Software License
Classifier: Operating System :: OS Independent
Classifier: Programming Language :: Python :: 3
Classifier: Programming Language :: Python :: 3.7
Classifier: Programming Language :: Python :: 3.8
License-File: LICENSE
Requires-Dist: basicsr (>=1.4.2)
Requires-Dist: facexlib (>=0.2.5)
Requires-Dist: lmdb
Requires-Dist: numpy
Requires-Dist: opencv-python
Requires-Dist: pyyaml
Requires-Dist: scipy
Requires-Dist: tb-nightly
Requires-Dist: torch (>=1.7)
Requires-Dist: torchvision
Requires-Dist: tqdm
Requires-Dist: yapf
